{
  "anforande": {
    "dok_hangar_id": "5035204",
    "dok_id": "H60999",
    "dok_titel": "Protokoll 2018/19:99 Tisdagen den 4 juni",
    "dok_rm": "2018/19",
    "dok_nummer": "99",
    "dok_datum": "2019-06-04 00:00:00",
    "avsnittsrubrik": "(forts.) Handelspolitik (forts. NU13)",
    "underrubrik": null,
    "kammaraktivitet": null,
    "anforande_id": "e3bacb9d-5197-e911-911f-901b0eac4c70",
    "anforande_nummer": "69",
    "talare": "Lorena Delgado Varas (V)",
    "parti": "V",
    "anforandetext": "<p>Fru talman! I det stora hela, om vi ska titta på faktiska siffror, gynnar säkert frihandelsavtal många länder. Men man kan titta lite närmare, och detta bjuder jag in dig att göra, Tobias Andersson! Möt de organisationer som jobbar med mänskliga rättigheter, urfolk och så vidare i andra länder så ska du se att det finns stora grupper i dessa samhällen som inte får del av det som handeln ger. I många fall förlorar de faktiskt på den.</p><p>Vissa industrier, till exempel gruvindustrin och stora livsmedelsproducenter, stärks, och i och med detta förstörs de marker som urfolken har, liksom vattendrag i olika länder. Det finns stora problem med de handelsavtal som sätts på plats i dag.</p><p>Jag är säker på att Sverigedemokraterna aldrig kommer att rösta för något som de inte ser är tillräckligt bra utfört. Vi ser stora problem med de handelsavtal som läggs fram i dag, och det är oftast stora företag som är inblandade i att ta fram dem. Fackföreningar, urfolksorganisationer och så vidare är inte med i lika stor utsträckning när handelsavtal tas fram.</p><p>Jag undrar därför: Är ni villiga att rösta för saker som ni inte tycker är tillräckligt bra?</p>",
    "intressent_id": "0852475703226",
    "rel_dok_id": null,
    "replik": "Y",
    "systemdatum": "2019-06-25 16:01:21"
  }
}