{
  "anforande": {
    "dok_hangar_id": "5098474",
    "dok_id": "H809127",
    "dok_titel": "Protokoll 2020/21:127 Onsdagen den 26 maj",
    "dok_rm": "2020/21",
    "dok_nummer": "127",
    "dok_datum": "2021-05-26 00:00:00",
    "avsnittsrubrik": "Barn som bevittnar brott ",
    "underrubrik": "",
    "kammaraktivitet": "ärendedebatt",
    "anforande_id": "99e852a9-3416-ec11-9160-901b0e9b71a0",
    "anforande_nummer": "12",
    "talare": "Ellen Juntti (M)",
    "parti": "M",
    "anforandetext": "<p>Herr talman! Det finns ju en mängdrabatt. Vi moderater har i flera år sagt att vi vill att dagens regler ska tas bort, för de är helt uppåt väggarna fel. Om man begår flera brott som behandlas i samma rättegång får man rabatt. Det grövsta brottet får man fullt straff för. Redan för det andra brottet får man dock 50 procents rabatt, och för det tredje brottet får man 70 procents rabatt.</p><p>Om en gärningsman är åtalad för grov kvinnofridskränkning och grov barnfridskränkning i samma mål kommer han att få fullt straff för det grövsta brottet, mängdrabatt för det näst grövsta och så vidare. Men själva brottet är ju ett samlat brott. I det brottet ligger redan flera brott, men själva brottet blir grov barnfridskränkning och grov kvinnofridskränkning.</p>",
    "intressent_id": "0144048894712",
    "rel_dok_id": "H801JuU35",
    "replik": "Y",
    "systemdatum": "2021-09-15 16:53:49"
  }
}